odoo/addons/hr_employee_digitized_signature/README.rst
odoo/addons/hr_employee_digitized_signature/__init__.py
odoo/addons/hr_employee_digitized_signature/__manifest__.py
odoo/addons/hr_employee_digitized_signature/i18n/de.po
odoo/addons/hr_employee_digitized_signature/i18n/es.po
odoo/addons/hr_employee_digitized_signature/i18n/es_AR.po
odoo/addons/hr_employee_digitized_signature/i18n/hr_employee_digitized_signature.pot
odoo/addons/hr_employee_digitized_signature/i18n/it.po
odoo/addons/hr_employee_digitized_signature/models/__init__.py
odoo/addons/hr_employee_digitized_signature/models/hr_employee.py
odoo/addons/hr_employee_digitized_signature/readme/CONTRIBUTORS.rst
odoo/addons/hr_employee_digitized_signature/readme/DESCRIPTION.rst
odoo/addons/hr_employee_digitized_signature/static/description/icon.png
odoo/addons/hr_employee_digitized_signature/static/description/index.html
odoo/addons/hr_employee_digitized_signature/views/hr_employee_views.xml
odoo_addon_hr_employee_digitized_signature-16.0.1.0.0.8.dist-info/METADATA
odoo_addon_hr_employee_digitized_signature-16.0.1.0.0.8.dist-info/WHEEL
odoo_addon_hr_employee_digitized_signature-16.0.1.0.0.8.dist-info/top_level.txt
odoo_addon_hr_employee_digitized_signature-16.0.1.0.0.8.dist-info/RECORD
